SpreadPy/AnalyticalUtils.py
SpreadPy/IOUtils.py
SpreadPy/SpreadingModel.py
SpreadPy/__init__.py
SpreadPy/Models/__init__.py
SpreadPy/Models/models.py
SpreadPy/Tests/__init__.py
SpreadPy/Tests/test.py
SpreadPy-1.0.0.dist-info/LICENSE
SpreadPy-1.0.0.dist-info/METADATA
SpreadPy-1.0.0.dist-info/WHEEL
SpreadPy-1.0.0.dist-info/top_level.txt
SpreadPy-1.0.0.dist-info/RECORD
