Metadata-Version: 2.1
Name: SpreadPy
Version: 1.0.0
Summary: SpreadPy: Semantic Processing Simulation in Python
Home-page: https://github.com/dsalvaz/SpreadPy/
Author: ['Salvatore Citraro']
Author-email: salvatore.citraro@isti.cnr.it
License: BSD-Clause-2
Classifier: Development Status :: 4 - Beta
Classifier: Intended Audience :: Developers
Classifier: Topic :: Software Development :: Build Tools
Classifier: License :: OSI Approved :: BSD License
Classifier: Operating System :: OS Independent
Classifier: Programming Language :: Python :: 3
License-File: LICENSE
Requires-Dist: six
Requires-Dist: numpy
Requires-Dist: tqdm
Requires-Dist: networkx
Requires-Dist: matplotlib
Requires-Dist: pandas
Requires-Dist: nltk
Requires-Dist: scipy
